lasvegas/__init__.py
lasvegas/game.py
lasvegas/interactive.py
lasvegas/act/__init__.py
lasvegas/act/_utils.py
lasvegas/act/player.py
lasvegas/act/policy.py
lasvegas/act/rollicy.py
lasvegas/core/__init__.py
lasvegas/core/env.py
lasvegas/core/rules.py
lasvegas-0.2.0.dist-info/METADATA
lasvegas-0.2.0.dist-info/WHEEL
lasvegas-0.2.0.dist-info/licenses/LICENSE
lasvegas-0.2.0.dist-info/RECORD
