Metadata-Version: 2.1
Name: lasvegas
Version: 0.2.0
Summary: Las Vegas boardgame – API
Project-URL: Homepage, https://github.com/eliegoudout/lasvegas
Project-URL: Bug Tracker, https://github.com/eliegoudout/lasvegas/issues
Author-email: Élie Goudout <eliegoudout@hotmail.com>
License: MIT License
License-File: LICENSE
Classifier: License :: OSI Approved :: MIT License
Classifier: Operating System :: OS Independent
Classifier: Programming Language :: Python :: 3
Requires-Python: ~=3.10
Requires-Dist: numpy~=1.22
Requires-Dist: tabulate~=0.9
Requires-Dist: tqdm~=4.63
